Metadata-Version: 2.1
Name: metodosget
Version: 1.0
Summary: Ejercicio Final
Author: Oscar Caraballero Galvez
Author-email: xxx@gmail.com
License: MIT
Keywords: pokemon
Classifier: Development Status :: 3 - Alpha
Classifier: Intended Audience :: Developers
Classifier: Topic :: Software Development :: Build Tools
Classifier: License :: OSI Approved :: MIT License
Classifier: Programming Language :: Python :: 3
Classifier: Programming Language :: Python :: 3.7
Classifier: Programming Language :: Python :: 3.8
Classifier: Programming Language :: Python :: 3.9
Classifier: Programming Language :: Python :: 3.10
Classifier: Programming Language :: Python :: 3.11
